fluentcms_twitterfeed/__init__.py
fluentcms_twitterfeed/content_plugins.py
fluentcms_twitterfeed/models.py
fluentcms_twitterfeed/locale/ru/LC_MESSAGES/django.mo
fluentcms_twitterfeed/locale/ru/LC_MESSAGES/django.po
fluentcms_twitterfeed/migrations/0001_initial.py
fluentcms_twitterfeed/migrations/0002_auto_20180509_0412.py
fluentcms_twitterfeed/migrations/__init__.py
fluentcms_twitterfeed/south_migrations/0001_initial.py
fluentcms_twitterfeed/south_migrations/__init__.py
fluentcms_twitterfeed/templates/fluentcms_twitterfeed/base.html
fluentcms_twitterfeed/templates/fluentcms_twitterfeed/recent_entries.html
fluentcms_twitterfeed/templates/fluentcms_twitterfeed/search.html
fluentcms_twitterfeed/templatetags/__init__.py
fluentcms_twitterfeed/templatetags/twitterfeed_tags.py
fluentcms_twitterfeed-1.0.3.dist-info/AUTHORS
fluentcms_twitterfeed-1.0.3.dist-info/LICENSE
fluentcms_twitterfeed-1.0.3.dist-info/METADATA
fluentcms_twitterfeed-1.0.3.dist-info/WHEEL
fluentcms_twitterfeed-1.0.3.dist-info/top_level.txt
fluentcms_twitterfeed-1.0.3.dist-info/RECORD
