Metadata-Version: 2.1
Name: fluentcms-twitterfeed
Version: 1.0.3
Summary: Twitter feed widget for django-fluent-contents
Home-page: https://github.com/bashu/fluentcms-twitterfeed
Author: Basil Shubin
Author-email: basil.shubin@gmail.com
License: Apache License, Version 2.0
Download-URL: https://github.com/bashu/fluentcms-twitterfeed/zipball/master
Platform: UNKNOWN
Classifier: Development Status :: 4 - Beta
Classifier: Environment :: Web Environment
Classifier: Framework :: Django
Classifier: Intended Audience :: Developers
Classifier: License :: OSI Approved :: Apache Software License
Classifier: Operating System :: OS Independent
Classifier: Programming Language :: Python
Classifier: Programming Language :: Python :: 2.6
Classifier: Programming Language :: Python :: 2.7
Classifier: Programming Language :: Python :: 3
Classifier: Programming Language :: Python :: 3.3
Classifier: Topic :: Internet :: WWW/HTTP
Classifier: Topic :: Internet :: WWW/HTTP :: Dynamic Content
Classifier: Topic :: Software Development :: Libraries :: Python Modules
Requires: Django (>=1.4)
Requires-Dist: django-fluent-contents (>=1.0)
Requires-Dist: twitter-text (>2.0)
